planship_openapi_gen/__init__.py
planship_openapi_gen/api_client.py
planship_openapi_gen/api_response.py
planship_openapi_gen/configuration.py
planship_openapi_gen/exceptions.py
planship_openapi_gen/py.typed
planship_openapi_gen/rest.py
planship_openapi_gen/api/__init__.py
planship_openapi_gen/api/auth_api.py
planship_openapi_gen/api/customer_subscriptions_api.py
planship_openapi_gen/api/customers_api.py
planship_openapi_gen/api/entitlements_api.py
planship_openapi_gen/api/health_api.py
planship_openapi_gen/api/metered_usage_api.py
planship_openapi_gen/api/products_api.py
planship_openapi_gen/api/public_api.py
planship_openapi_gen/api/subscription_customers_api.py
planship_openapi_gen/api/subscriptions_api.py
planship_openapi_gen/models/__init__.py
planship_openapi_gen/models/bucket_usage.py
planship_openapi_gen/models/customer.py
planship_openapi_gen/models/customer_in_db_base.py
planship_openapi_gen/models/customer_subscription_with_plan.py
planship_openapi_gen/models/http_validation_error.py
planship_openapi_gen/models/id_name_orm_base.py
planship_openapi_gen/models/id_name_slug_orm_base.py
planship_openapi_gen/models/lever.py
planship_openapi_gen/models/lever_usage.py
planship_openapi_gen/models/location_inner.py
planship_openapi_gen/models/metered_usage_in.py
planship_openapi_gen/models/metering_record.py
planship_openapi_gen/models/organization_customer_create.py
planship_openapi_gen/models/plan.py
planship_openapi_gen/models/plan_entitlement.py
planship_openapi_gen/models/plan_in_db_base.py
planship_openapi_gen/models/plan_in_list.py
planship_openapi_gen/models/plan_subscription_create.py
planship_openapi_gen/models/product.py
planship_openapi_gen/models/subscription_create.py
planship_openapi_gen/models/subscription_customer.py
planship_openapi_gen/models/subscription_customer_add.py
planship_openapi_gen/models/subscription_customer_in_db_base.py
planship_openapi_gen/models/subscription_update_with_slugs.py
planship_openapi_gen-1.0.0.dist-info/METADATA
planship_openapi_gen-1.0.0.dist-info/WHEEL
planship_openapi_gen-1.0.0.dist-info/top_level.txt
planship_openapi_gen-1.0.0.dist-info/RECORD
